{
  "/Cicada2301/blog-1a0": {
    "__comp": "a6aa9e1f",
    "__context": {
      "plugin": "471ee7e7"
    },
    "sidebar": "814f3328",
    "items": [
      {
        "content": "7661071f"
      },
      {
        "content": "f4f34a3a"
      },
      {
        "content": "8717b14a"
      },
      {
        "content": "925b3f96"
      }
    ],
    "metadata": "489f8672"
  },
  "/Cicada2301/blog/archive-ab7": {
    "__comp": "9e4087bc",
    "__context": {
      "plugin": "471ee7e7"
    },
    "archive": "326cbc53"
  },
  "/Cicada2301/blog/first-blog-post-dc9": {
    "__comp": "ccc49370",
    "__context": {
      "plugin": "471ee7e7"
    },
    "sidebar": "814f3328",
    "content": "e273c56f"
  },
  "/Cicada2301/blog/long-blog-post-293": {
    "__comp": "ccc49370",
    "__context": {
      "plugin": "471ee7e7"
    },
    "sidebar": "814f3328",
    "content": "73664a40"
  },
  "/Cicada2301/blog/mdx-blog-post-b30": {
    "__comp": "ccc49370",
    "__context": {
      "plugin": "471ee7e7"
    },
    "sidebar": "814f3328",
    "content": "59362658"
  },
  "/Cicada2301/blog/tags-4f6": {
    "__comp": "01a85c17",
    "__context": {
      "plugin": "471ee7e7"
    },
    "sidebar": "814f3328",
    "tags": "1783b3b1"
  },
  "/Cicada2301/blog/tags/docusaurus-8c6": {
    "__comp": "6875c492",
    "__context": {
      "plugin": "471ee7e7"
    },
    "sidebar": "814f3328",
    "items": [
      {
        "content": "7661071f"
      },
      {
        "content": "f4f34a3a"
      },
      {
        "content": "8717b14a"
      },
      {
        "content": "925b3f96"
      }
    ],
    "tag": "c98ea0fd",
    "listMetadata": "50dce65f"
  },
  "/Cicada2301/blog/tags/facebook-0b6": {
    "__comp": "6875c492",
    "__context": {
      "plugin": "471ee7e7"
    },
    "sidebar": "814f3328",
    "items": [
      {
        "content": "7661071f"
      }
    ],
    "tag": "4605677a",
    "listMetadata": "96158ebb"
  },
  "/Cicada2301/blog/tags/hello-972": {
    "__comp": "6875c492",
    "__context": {
      "plugin": "471ee7e7"
    },
    "sidebar": "814f3328",
    "items": [
      {
        "content": "7661071f"
      },
      {
        "content": "8717b14a"
      }
    ],
    "tag": "9eefe675",
    "listMetadata": "02768d39"
  },
  "/Cicada2301/blog/tags/hola-a8b": {
    "__comp": "6875c492",
    "__context": {
      "plugin": "471ee7e7"
    },
    "sidebar": "814f3328",
    "items": [
      {
        "content": "925b3f96"
      }
    ],
    "tag": "4b12f41f",
    "listMetadata": "aa30ee97"
  },
  "/Cicada2301/blog/welcome-d79": {
    "__comp": "ccc49370",
    "__context": {
      "plugin": "471ee7e7"
    },
    "sidebar": "814f3328",
    "content": "d9f32620"
  },
  "/Cicada2301/markdown-page-974": {
    "__comp": "1f391b9e",
    "__context": {
      "plugin": "c0371cb1"
    },
    "content": "393be207"
  },
  "/Cicada2301/docs-359": {
    "__comp": "1be78505",
    "__context": {
      "plugin": "372a3e00"
    },
    "versionMetadata": "935f2afb"
  },
  "/Cicada2301/docs/category/tutorial---basics-8eb": {
    "__comp": "14eb3368",
    "categoryGeneratedIndex": "055b485a"
  },
  "/Cicada2301/docs/category/tutorial---extras-6cb": {
    "__comp": "14eb3368",
    "categoryGeneratedIndex": "373d2340"
  },
  "/Cicada2301/docs/cOSINT-9e9": {
    "__comp": "17896441",
    "content": "e226798f"
  },
  "/Cicada2301/docs/intro-b6d": {
    "__comp": "17896441",
    "content": "0e384e19"
  },
  "/Cicada2301/docs/MaoMao/random-76d": {
    "__comp": "17896441",
    "content": "36ae6d90"
  },
  "/Cicada2301/docs/Morsa/rename-655": {
    "__comp": "17896441",
    "content": "30b8322d"
  },
  "/Cicada2301/docs/OSINT/people-b34": {
    "__comp": "17896441",
    "content": "3a776330"
  },
  "/Cicada2301/docs/tutorial-basics/congratulations-469": {
    "__comp": "17896441",
    "content": "822bd8ab"
  },
  "/Cicada2301/docs/tutorial-basics/create-a-blog-post-d6c": {
    "__comp": "17896441",
    "content": "533a09ca"
  },
  "/Cicada2301/docs/tutorial-basics/create-a-document-692": {
    "__comp": "17896441",
    "content": "1e4232ab"
  },
  "/Cicada2301/docs/tutorial-basics/create-a-page-677": {
    "__comp": "17896441",
    "content": "5c868d36"
  },
  "/Cicada2301/docs/tutorial-basics/deploy-your-site-fc8": {
    "__comp": "17896441",
    "content": "f55d3e7a"
  },
  "/Cicada2301/docs/tutorial-basics/markdown-features-82b": {
    "__comp": "17896441",
    "content": "18c41134"
  },
  "/Cicada2301/docs/tutorial-extras/manage-docs-versions-f38": {
    "__comp": "17896441",
    "content": "dff1c289"
  },
  "/Cicada2301/docs/tutorial-extras/translate-your-site-48d": {
    "__comp": "17896441",
    "content": "e44a2883"
  },
  "/Cicada2301/-90d": {
    "__comp": "c4f5d8e4",
    "__context": {
      "plugin": "c0371cb1"
    },
    "config": "5e9f5e1a"
  }
}